eznotify/__init__.py
eznotify-0.0.2.dist-info/LICENSE.txt
eznotify-0.0.2.dist-info/METADATA
eznotify-0.0.2.dist-info/WHEEL
eznotify-0.0.2.dist-info/top_level.txt
eznotify-0.0.2.dist-info/RECORD
