Metadata-Version: 2.1
Name: eznotify
Version: 0.0.2
Summary: eznotify the easiest way to send notifications to windows 10
Home-page: https://pypi.org/project/eznotify/
Author: Eshan Nalajala
Author-email: eshan.nalajala@gmail.com
License: UNKNOWN
Platform: UNKNOWN
Classifier: Programming Language :: Python :: 3
Classifier: License :: OSI Approved :: MIT License
Classifier: Operating System :: OS Independent
Requires-Python: >=3.6
Requires-Dist: win10toast
